Workbook

Sheet 前言卡
A1: 所有使用 | B1: 这个背景颜色 | D1: 的单元格均为自动计算
A2: 随便改会弄坏自动表 | C2: （基本上手动填的就是白色底色）
A3: 版权所有： | B3: 塔索里安 | C3: Cyberpunk：RED
B5: 自动卡作者： | E5: 扩展作者： | H5: 扩展自动卡作者：
B6: @zcrss | E6: @人间观察 | H6: @黑客真的不弱的
B7: 特别鸣谢以上！
A8: 二改： | C8: 三改基础公式来自 | F8: 四改：
A9: @光明大主教 | C9: 禾仓石/代号乌鸦 | F9: 猫
A11: 注意：
A12: 1、改造的人物卡和之前相比，车卡复杂度略有提升，原因是把装备库存、背包、购物都分开了。自动计算金钱的时候只根据购物记录和行动记录算出，然后把物品存背包，这样就不会因为物品消耗而导致金额返还了。
A17: 2、属性点和技能点和初始资金请按GM所给的开卡条件填写
A23: 修改记录
A24: 46190 | B24: 调整了义体卡，细分了人性上限损失和人性损失，将背包卡改为单行方便复制粘贴，更新随版本变化的部分速查表的数值，调整部分格式
A25: 46200 | B25: 鲨包1.9更新伤势表，微调网行卡方便复制粘贴
A26: 46203 | B26: 修复部分公式错误，调整往来记录-IP表，增加载具卡，增加更多自动识别，重制装备卡，钱包及衣食住行移动到购物助手中，方便且集中消费
A27: 46230 | B27: 完善ACPA卡
A28: 46245 | B28: 鲨包1.91修改伤势表，技能表-乐器演奏优化

Sheet 人物卡
C2: 基础信息 | J2: 人物属性 | O2: 调整 | P2: 结果 | T2: 技能 | AF2: 战斗技能 | AH2: 调整 | AI2: 加点 | AJ2: 技能基准 | AM2: 专长 | AV2: 武器
Z3: 请把括号内容改成你实际的选择 | AF3: 搏击 | AI3: 2 | AJ3: =AH3+AI3+$P$8 -> 0
J4: 智力INT | P4: =K4+O4 -> 0 | T4: 感官技能 | V4: 调整 | W4: 加点 | X4: 技能基准 | Z4: 教育技能 | AB4: 调整 | AC4: 加点 | AD4: 技能基准 | AF4: 闪避 | AI4: 2 | AJ4: =AH4+AI4+$P$8 -> 0 | AN4: 专长 | AO4: 描述 | AV4: 武器名称 | AX4: 可靠性 | AY4: 射速/攻速 | AZ4: 剩余子弹 | BA4: 精准 | BB4: 全自动弹幕 | BC4: 伤害 | BD4: 弹容量（口径） | BE4: 穿甲等级
T5: 专注 | W5: 2 | X5: =V5+W5+$P$14 -> 2 | Z5: 会计 | AD5: =AC5+AB5+$P$4 -> 0 | AF5: [x2] | AG5: （武术） | AJ5: =AH5+ROUNDDOWN(AI5/2,0)+$P$8 -> -2 | AV5: =武器卡!C5 -> 达拉理工“吠舍”自动手枪 | AX5: =武器卡!D5 -> 低 | AY5: =武器卡!F5 -> 3 | BA5: =武器卡!H5 -> -1 | BB5: =武器卡!K5 -> 4x8 | BC5: =武器卡!L5 -> 2D6 | BD5: =武器卡!G5 -> 20（.22lr） | BE5: =武器卡!M5 -> 手枪
J6: 反应REF | P6: =K6+O6-BB20 -> -2 | T6: 隐藏/发现物品 | X6: =V6+W6+$P$4 -> 0 | Z6: 驯兽 | AD6: =AC6+AB6+$P$4 -> 0 | AF6: [x2] | AG6: （武术） | AJ6: =AH6+ROUNDDOWN(AI6/2,0)+$P$8 -> -2
T7: 唇语 | X7: =V7+W7+$P$4 -> 0 | Z7: 官场 | AD7: =AC7+AB7+$P$4 -> 0 | AF7: [x2] | AG7: （武术） | AJ7: =AH7+ROUNDDOWN(AI7/2,0)+$P$8 -> -2 | AV7: =武器卡!C15 -> 单镰 | AX7: =武器卡!D15 -> 中 | AY7: =武器卡!F15 -> 2 | BA7: =武器卡!H15 -> 2+1 | BB7: =武器卡!K15 -> 0 | BC7: =武器卡!L15 -> 1D6 | BD7: =武器卡!G15 -> 0 | BE7: =武器卡!M15 -> 全威力
J8: 敏捷DEX | P8: =K8+O8-BB20 -> -2 | T8: 察觉 | W8: 2 | X8: =V8+W8+$P$4 -> 2 | Z8: 商务 | AD8: =AC8+AB8+$P$4 -> 0 | AF8: 近战武器 | AJ8: =AH8+AI8+$P$8 -> -2
T9: 追踪 | X9: =V9+W9+$P$4 -> 0 | Z9: 写作 | AD9: =AC9+AB9+$P$4 -> 0 | AF9: 远程武器技能 | AH9: 调整 | AI9: 加点 | AJ9: 技能基准 | AV9: =武器卡!C25 -> 大龙 剑鞭 | AX9: =武器卡!D25 -> 中 | AY9: =武器卡!F25 -> 3或2 | BA9: =武器卡!H25 -> 1+1 | BB9: =武器卡!K25 -> 0 | BC9: =武器卡!L25 -> 5D6 | BD9: =武器卡!G25 -> 0 | BE9: =武器卡!M25 -> 全威力
J10: 技术TECH | P10: =K10+O10 -> 0 | T10: 身体技能 | V10: 调整 | W10: 加点 | X10: 技能基准 | Z10: 犯罪学 | AD10: =AC10+AB10+$P$4 -> 0 | AF10: 弓术 | AJ10: =AH10+AI10+$P$6 -> -2
T11: 运动 | W11: 2 | X11: =V11+W11+$P$8 -> 0 | Z11: 密码学 | AD11: =AC11+AB11+$P$4 -> 0 | AF11: [x2]自动武器 | AJ11: =AH11+ROUNDDOWN(AI11/2,0)+$P$6 -> -2 | AV11: =武器卡!C35 -> 0 | AX11: =武器卡!D35 -> 0 | AY11: =武器卡!F35 -> 0 | BA11: =武器卡!H35 -> 0 | BB11: =武器卡!K35 -> 0 | BC11: =武器卡!L35 -> 0 | BD11: =武器卡!G35 -> 0 | BE11: =武器卡!M35 -> 0
J12: 酷COOL | P12: =K12+O12 -> 0 | T12: 柔韧 | X12: =V12+W12+$P$8 -> -2 | Z12: 推理 | AD12: =AC12+AB12+$P$4 -> 0 | AF12: 手枪 | AJ12: =AH12+AI12+$P$6 -> -2
T13: 舞蹈 | X13: =V13+W13+$P$8 -> -2 | Z13: 通识 | AC13: 2 | AD13: =AC13+AB13+$P$4 -> 2 | AF13: [x2]重武器 | AJ13: =AH13+ROUNDDOWN(AI13/2,0)+$P$6 -> -2
J14: 意志WILL | P14: =K14+O14 -> 0 | T14: 忍耐 | X14: =V14+W14+$P$14 -> 0 | Z14: 赌博 | AD14: =AC14+AB14+$P$4 -> 0 | AF14: 长管武器 | AJ14: =AH14+AI14+$P$6 -> -2
C15: 头像 | T15: 抗折磨/耐药 | X15: =V15+W15+$P$14 -> 0 | Z15: 图书馆检索 | AD15: =AC15+AB15+$P$4 -> 0 | AF15: 社交技能 | AH15: 调整 | AI15: 加点 | AJ15: 技能基准
C16: 玩家 | J16: 运气LUCK | P16: =K16+O16 -> 0 | T16: 潜行 | W16: 2 | X16: =V16+W16+$P$8 -> 0 | Z16: 科学 | AF16: 贿赂 | AJ16: =AH16+AI16+$P$12 -> 0
C17: 姓名 | T17: 操作技能 | V17: 调整 | W17: 加点 | X17: 技能基准 | Z17: ┣→ | AA17: （学科） | AD17: =AC17+AB17+$P$4 -> 0 | AF17: 交谈 | AI17: 2 | AJ17: =AH17+AI17+$P$22 -> 2 | AV17: 护甲
C18: 外号 | J18: 移速MOV | P18: =K18+O18-BB20 -> -2 | T18: 陆地载具 | X18: =V18+W18+$P$6 -> -2 | Z18: ┣→ | AA18: （学科） | AD18: =AC18+AB18+$P$4 -> 0 | AF18: 察言观色 | AI18: 2 | AJ18: =AH18+AI18+$P$22 -> 2
C19: 年龄 | E19: 性别 | T19: [x2]空中载具 | X19: =V19+ROUNDDOWN(W19/2,0)+$P$6 -> -2 | Z19: ┗→ | AA19: （学科） | AD19: =AC19+AB19+$P$4 -> 0 | AF19: 审讯 | AJ19: =AH19+AI19+$P$12 -> 0 | AV19: 部位 | AW19: 护甲名称 | AY19: 剩余SP | AZ19: 完整SP | BA19: EV妨碍值 | BB19: EV合计 | BC19: 特性备注 | BE19: 护甲等级
C20: 故乡 | J20: 体格BODY | P20: =K20+O20 -> 0 | T20: 水上载具 | X20: =V20+W20+$P$6 -> -2 | Z20: 战术 | AD20: =AC20+AB20+$P$4 -> 0 | AF20: 说服 | AI20: 2 | AJ20: =AH20+AI20+$P$12 -> 2 | AV20: 头部 | AW20: =防具卡!D5 -> 老兵头盔 | AZ20: =防具卡!G5 -> 11 | BA20: =防具卡!H5 -> 1 | BB20: =MAX(BA20:BA37) -> 2 | BC20: =防具卡!K5 -> 跳弹 | BE20: =LOOKUP(AY20, {0,4,10,15,20,26,33,41}, {"无甲","轻甲","中甲","重甲","超重甲","战车甲","坦克","共事"}) -> 无甲
C21: 等级 | E21: 声望 | F21: =往来记录!L61 -> 0 | T21: 骑术 | X21: =V21+W21+$P$6 -> -2 | Z21: 野外生存 | AD21: =AC21+AB21+$P$4 -> 0 | AF21: 个人装扮 | AJ21: =AH21+AI21+$P$12 -> 0
C22: 原生家庭 | J22: 共情EMP | P22: =K22+O22+O23 -> 0 | T22: 表演技能 | V22: 调整 | W22: 加点 | X22: 技能基准 | Z22: 口语表达 | AF22: 街头智慧 | AJ22: =AH22+AI22+$P$12 -> 0 | AV22: 面部 | AW22: =防具卡!D6 -> 0 | AZ22: =防具卡!G6 -> 0 | BA22: =防具卡!H6 -> 0 | BC22: =防具卡!K6 -> 0 | BE22: =LOOKUP(AY22, {0,4,10,15,20,26,33,41}, {"无甲","轻甲","中甲","重甲","超重甲","战车甲","坦克","共事"}) -> 无甲
O23: =INT(MOD(K32,100)/10)-K22 -> 0 | T23: 扮演/伪装 | X23: =V23+W23+$P$12 -> 0 | Z23: ┣→ | AA23: 街头俚语 | AC23: 2 | AD23: =AC23+AB23+$P$4 -> 2 | AF23: 交易 | AJ23: =AH23+AI23+$P$12 -> 0
J24: 可用点数 | O24: 先攻 调整 | T24: 乐器演奏 | Z24: ┣→ | AA24: （母语） | AB24: 4 | AD24: =AC24+AB24+$P$4 -> 4 | AF24: 服饰与风格 | AJ24: =AH24+AI24+$P$12 -> 0 | AV24: 躯干 | AW24: =防具卡!D7 -> 轻型装甲夹克 | AZ24: =防具卡!G7 -> 9 | BA24: =防具卡!H7 -> 0 | BC24: =防具卡!K7 -> 防震内衬 | BE24: =LOOKUP(AY24, {0,4,10,15,20,26,33,41}, {"无甲","轻甲","中甲","重甲","超重甲","战车甲","坦克","共事"}) -> 无甲
C25: 职业 | J25: 剩余点数 | K25: =K24-SUM(K4:K22) -> 0 | T25: ┣→ | U25: 打击乐器 | X25: =V25+W25+$P$10 -> 0 | Z25: ┗→ | AA25: （外语） | AD25: =AC25+AB25+$P$4 -> 0 | AF25: 技术技能 | AH25: 调整 | AI25: 加点 | AJ25: 技能基准
C26: 职业兼职规则以RF为准 | T26: ┣→ | U26: 管类乐器 | X26: =V26+W26+$P$10 -> 0 | Z26: 本地专家 | AF26: 空中载具技术 | AJ26: =AH26+AI26+$P$10 -> 0 | AV26: 插板 | AW26: =防具卡!D8 -> 0 | AZ26: =防具卡!G8 -> 0 | BA26: =防具卡!H8 -> 0 | BC26: =防具卡!K8 -> 0 | BE26: =LOOKUP(AY26, {0,4,10,15,20,26,33,41}, {"无甲","轻甲","中甲","重甲","超重甲","战车甲","坦克","共事"}) -> 无甲
C27: 主职业 | E27: 等级 | T27: ┣→ | U27: 弦类乐器 | X27: =V27+W27+$P$10 -> 0 | Z27: ┣→ | AA27: （你家） | AC27: 2 | AD27: =AC27+AB27+$P$4 -> 2 | AF27: 基础技术 | AJ27: =AH27+AI27+$P$10 -> 0
J28: 状态 | T28: ┣→ | U28: 键盘乐器 | X28: =V28+W28+$P$10 -> 0 | Z28: ┣→ | AA28: （地区） | AD28: =AC28+AB28+$P$4 -> 0 | AF28: 赛博技术 | AJ28: =AH28+AI28+$P$10 -> 0 | AV28: 胳膊 | AW28: =防具卡!D9 -> 轻型装甲夹克 | AZ28: =防具卡!G9 -> 9 | BA28: =防具卡!H9 -> 0 | BC28: =防具卡!K9 -> 防震内衬 | BE28: =LOOKUP(AY28, {0,4,10,15,20,26,33,41}, {"无甲","轻甲","中甲","重甲","超重甲","战车甲","坦克","共事"}) -> 无甲
C29: 兼职1 | E29: 等级 | J29: 影响血量的意志与体格直接加在人物属性 | T29: ┗→ | U29: 电子乐器 | X29: =V29+W29+$P$10 -> 0 | Z29: ┗→ | AA29: （地区） | AD29: =AC29+AB29+$P$4 -> 0 | AF29: [x2]爆破学 | AJ29: =AH29+ROUNDDOWN(AI29/2,0)+$P$10 -> 0
J30: 生命值 | N30: / | O30: =10+ROUNDUP((K20+K14)/2,0)*5 -> 10 | AF30: [x2]电子/安全技术 | AJ30: =AH30+ROUNDDOWN(AI30/2,0)+$P$10 -> 0 | AV30: 腿部 | AW30: =防具卡!D10 -> 嵌板式防弹裤 | AZ30: =防具卡!G10 -> 15 | BA30: =防具卡!H10 -> 2 | BC30: =防具卡!K10 -> 复合衬垫（1） | BE30: =LOOKUP(AY30, {0,4,10,15,20,26,33,41}, {"无甲","轻甲","中甲","重甲","超重甲","战车甲","坦克","共事"}) -> 无甲
C31: 兼职2 | E31: 等级 | S31: 职业能力 | AF31: 急救 | AI31: 2 | AJ31: =AH31+AI31+$P$10 -> 2
J32: 人性值 | K32: =MAX(IF(ISBLANK(K22),0,MIN(10*K22-义体卡!I5+义体卡!P16,O32)),0) -> 0 | N32: / | O32: =MAX(10*K22-义体卡!J5,0) -> 0 | T32: 能力名称 | V32: 使用记录 | AF32: [x2]强化急救 | AJ32: =AH32+ROUNDDOWN(AI32/2,0)+$P$10 -> 0 | AV32: 盾牌 | AW32: =防具卡!D11 -> 0 | AZ32: =防具卡!G11 -> 0 | BA32: =防具卡!H11 -> 0 | BC32: =防具卡!K11 -> 0 | BE32: =LOOKUP(AY32, {0,4,10,15,20,26,33,41}, {"无甲","轻甲","中甲","重甲","超重甲","战车甲","坦克","共事"}) -> 无甲
C33: 兼职3 | E33: 等级 | AC33: 总点数 | AF33: 伪造 | AJ33: =AH33+AI33+$P$10 -> 0
J34: 请手动填写当前的生命值 | AC34: 剩余 | AF34: 地面载具技术 | AJ34: =AH34+AI34+$P$10 -> 0 | AV34: 赛博格 | AW34: =防具卡!D12 -> 0 | AZ34: =防具卡!G12 -> 0 | BA34: =防具卡!H12 -> 0 | BC34: =防具卡!K12 -> 0 | BE34: =LOOKUP(AY34, {0,4,10,15,20,26,33,41}, {"无甲","轻甲","中甲","重甲","超重甲","战车甲","坦克","共事"}) -> 无甲
C35: 兼职4 | E35: 等级 | J35: 伤势状态 | AC35: 总点数 | AF35: 绘画/速写/雕刻 | AJ35: =AH35+AI35+$P$10 -> 0
J36: =IF(K30=0,"致命伤",IF(K30<O30,IF(K30<O30/2,"重伤","轻伤"),"健康")) -> 致命伤 | AC36: 剩余 | AF36: 摄影/摄像 | AJ36: =AH36+AI36+$P$10 -> 0 | AV36: 掩体
C37: 兼职5 | E37: 等级 | AC37: 总点数 | AF37: 开锁 | AJ37: =AH37+AI37+$P$10 -> 0
J38: 伤势效果 | AC38: 剩余 | AF38: 扒窃 | AJ38: =AH38+AI38+$P$10 -> 0
C39: 兼职6 | E39: 等级 | J39: =IF(J36="健康","无",IF(J36="轻伤","无",IF(J36="重伤","所有动作检定-2",IF(J36="致命伤","所有动作的检定 -4，移速属性 -6（最低剩余 1）",2)))) -> 所有动作的检定 -4，移速属性 -6（最低剩余 1） | AC39: 总点数 | AF39: 海洋载具技术 | AJ39: =AH39+AI39+$P$10 -> 0
AC40: 剩余 | AF40: 武器技术 | AJ40: =AH40+AI40+$P$10 -> 0 | AV40: 口袋 | AW40: 可选规则以RF为准
C41: 兼职7 | E41: 等级 | J41: 救治难度 | AC41: 总点数
J42: {=IF(J36="健康","无",IF(J36="轻伤","10",IF(J36="重伤","13",IF(J36="致命伤","15",_xleta.XIRR))))} -> 15 | AC42: 剩余 | AF42: 可用点数 | AI42: 剩余 | AJ42: =AH42-SUM(W5:W9)-SUM(W11:W16)-SUM(W18:W21)-W23-SUM(W25:W29)-SUM(AC5:AC15)-SUM(AI3:AI8)-SUM(AI10:AI14)-SUM(AI16:AI24)-SUM(AI26:AI40)-SUM(AC17:AC21)-SUM(AC23:AC25)-SUM(AC27:AC29) -> -26 | AV42: 口袋位置 | AX42: 物品/数量 | AZ42: 物品/数量 | BB42: 物品/数量 | BD42: 物品/数量
C43: 兼职8 | E43: 等级 | AC43: 总点数 | AF43: 加点列浅红色标记的为必须点的基础加点，技能列红色[x2]的在加点列+2才会+1技能基准
J44: 严重伤势 | O44: 效果 | AC44: 剩余 | AN44: 备注
C45: 兼职9 | E45: 等级
C47: 备注
J53: 死亡豁免调整

Sheet 武器卡
C2: 武器 | D2: 属性会同步到人物卡界面，插件特效不会自动计算，请手动修改武器属性-以下为示例，使用前请删除
C4: 武器名称 | D4: 可靠性 | E4: 类型 | F4: 射速/攻速 | G4: 弹容量（口径） | H4: 精准 | I4: 持用手 | J4: 客制槽位 | K4: 全自动弹幕 | L4: 伤害 | M4: 穿甲等级 | N4: 隐藏等级
C5: 达拉理工“吠舍”自动手枪 | D5: 低 | E5: 中型手枪（自动） | F5: 3 | G5: 20（.22lr） | H5: -1 | I5: 单 | J5: 2 | K5: 4x8 | L5: 2D6 | M5: 手枪 | N5: 是
C6: 描述
C7: 低后座 达拉理工为街头交火提供的便携廉价选择。由廉价聚合物和水管钢材打印成的全自动手枪，使用.22单纯因为节省成本而使用的材料膛压不足，9mm的子弹会直接炸膛。
C8: 配件 | D8: 描述 | M8: 占用位置 | N8: 占用槽数
C9: 红外夜视镜 | D9: 减少你在黑暗条件下射击目标时所受到的惩罚，使其降为0。透过瞄准镜，你可以区分热肉和冷金属，但不能更具体地区分。例如，你无法从远处看到他们的品牌，或看到物体内部。 | M9: 瞄具 | N9: 1
C10: 消音器 | D10: 吸收枪口火焰和声音，不能做到完全无声，在不搭配亚音速弹药使用的情况下，只能保证在15m开外保持消音。搭配亚音速弹药可以做到全距离消音，就像打了个喷嚏一样。 | M10: 枪口 | N10: 1
C14: 武器名称 | D14: 可靠性 | E14: 类型 | F14: 射速/攻速 | G14: 弹容量（口径） | H14: 精准 | I14: 持用手 | J14: 客制槽位 | K14: 全自动弹幕 | L14: 伤害 | M14: 穿甲等级 | N14: 隐藏等级
C15: 单镰 | D15: 中 | E15: 轻型 | F15: 2 | H15: 2+1 | I15: 单 | L15: 1D6 | M15: 全威力 | N15: 是
C16: 描述
C17: 可以用来COS忍者，或者单纯用它来收麦子。
C18: 配件 | D18: 描述 | M18: 占用位置 | N18: 占用槽数
C19: 智刃链接 | D19: 为近战武器安装的智能链接，安装在握柄处。同样需要使用者有皮下握把或交互接口和神经链接才能与之相连。成功链接后，你的近战武器命中+1，且不会因为任何非主动原因导致脱手。 | M19: 特殊 | N19: /
C24: 武器名称 | D24: 可靠性 | E24: 类型 | F24: 射速/攻速 | G24: 弹容量（口径） | H24: 精准 | I24: 持用手 | J24: 客制槽位 | K24: 全自动弹幕 | L24: 伤害 | M24: 穿甲等级 | N24: 隐藏等级
C25: 大龙 剑鞭 | D25: 中 | E25: 重型 | F25: 3或2 | H25: 1+1 | I25: 双 | L25: 5D6 | M25: 全威力 | N25: 否
C26: 描述
C27: 一种在最新技术下打造的传武兵器，可长可短，攻击方式相当灵活。平时收纳时看起来只是一把普通中式长剑，但只要按一下刀柄上的按钮，就能变成一把锋利的长鞭。 特殊攻击模式：一回合有一次变更攻击模式的机会，可变更为长鞭，ROF-1.该模式下攻击范围+2m，也可以如霰弹枪一样对面前4m长6m宽的区域进行范围攻击，当使用后者的攻击模式时，伤害骰额外-1。.
C28: 配件 | D28: 描述 | M28: 占用位置 | N28: 占用槽数
C29: 智刃链接 | D29: 为近战武器安装的智能链接，安装在握柄处。同样需要使用者有皮下握把或交互接口和神经链接才能与之相连。成功链接后，你的近战武器命中+1，且不会因为任何非主动原因导致脱手。 | M29: 特殊 | N29: /
C34: 武器名称 | D34: 可靠性 | E34: 类型 | F34: 射速/攻速 | G34: 弹容量（口径） | H34: 精准 | I34: 持用手 | J34: 客制槽位 | K34: 全自动弹幕 | L34: 伤害 | M34: 穿甲等级 | N34: 隐藏等级
C36: 描述
C38: 配件 | D38: 描述 | M38: 占用位置 | N38: 占用槽数

Sheet 防具卡
C2: 护甲 | E2: 以下为示例，使用前请删除
C4: 护甲部位 | D4: 护甲名称 | E4: 稀有度 | F4: 合法外穿 | G4: 护甲SP | H4: 妨碍值EV | I4: 口袋容量 | J4: 描述 | K4: 特性
C5: 头部 | D5: 老兵头盔 | E5: N | F5: N | G5: 11 | H5: 1 | I5: / | J5: 跳弹 谁知道它参加过公司战争还是中美洲战争，也许参加过越南战争，说不定陪你爷爷的爷爷打过德国人。别指望它能挡住什么，但你可以相信奇迹。 | K5: 跳弹
C6: 面部
C7: 躯干 | D7: 轻型装甲夹克 | E7: R | F7: Y | G7: 9 | H7: 0 | I7: 2m | J7: 防震内衬 一些深入暗地采访的记者会使用的装甲夹克，精心设计的护板既不妨碍运动，又能抱住小命。它也是城市佣兵的一款非常常见的装束。 | K7: 防震内衬
C8: 插板
C9: 胳膊 | D9: 轻型装甲夹克 | E9: R | F9: Y | G9: 9 | H9: 0 | I9: 2m | J9: 防震内衬 一些深入暗地采访的记者会使用的装甲夹克，精心设计的护板既不妨碍运动，又能抱住小命。它也是城市佣兵的一款非常常见的装束。 | K9: 防震内衬
C10: 腿部 | D10: 嵌板式防弹裤 | E10: R | F10: Y | G10: 15 | H10: 2 | I10: 2s | J10: 复合衬垫（1）用防弹合金板和重型凯夫拉纤维缝制的裤子，能有效保护你的老二。 | K10: 复合衬垫（1）
C11: 盾牌
C12: 赛博格
C15: 时尚1 | D15: 作战 | E15: 以下为示例，使用前请删除
C17: 护甲部位 | D17: 护甲名称 | E17: 稀有度 | F17: 风格 | G17: 护甲SP | H17: 妨碍值EV | I17: 口袋容量 | J17: 描述 | K17: 特性
C18: 帽子 | D18: 罗夏™波动面具 | E18: R | F18: 机能异端主义 | G18: 0 | H18: 0 | I18: / | J18: 有些人不太喜欢让别人看清自己的脸色，又不想做那种有些疼还需要勤维护的义体手术，那这个全息面具就是为他们准备的。它通过全息投影技术将一整块罗夏墨迹测试投射在使用者的脸部，可以随使用者的心情自由变化图案。不过说句实话，那只是一滩对称的墨迹而已，谁能知道它到底代表了什么？（无法和12sp以上的头盔兼容） | K18: 他人无法对你察言观色
C19: 内搭
C20: 外套 | D20: 壮志凌云™ 飞行员夹克 | E20: SR | F20: 实用主义 | G20: 4 | H20: 0 | I20: 2m | J20: 时尚有时候是新潮，有时候也是复古。这套由芳纶纤维加人造皮革纺织的飞行员夹克就很好诠释了这一点。它既保暖又结实，集绝缘、保暖、防风、耐磨等优点于一身，号称穿50年都不会坏。同时附件还有自定义的魔术贴徽章，让你穿出属于自己的范。 | K20: 自带永不损坏的4sp， 服饰风格+1
C21: 下装 | D21: 壮志凌云™ 复古牛仔裤 | E21: SR | F21: 实用主义 | G21: 4 | H21: 0 | I21: 2s | J21: 牛仔裤一直是美国鼎盛时期的象征物，直到解体后的今日，它依然在街头巷尾流行。它的版式和材质和一百年前没有多大差别，即便如此，人们在这个时代依旧热爱通它。而它与皮夹克的搭配更是经典中的经典。 | K21: 自带永不损坏的4sp
C22: 配饰
C25: 时尚2 | D25: 日常 | E25: 以下为示例，使用前请删除
C27: 护甲部位 | D27: 护甲名称 | E27: 稀有度 | F27: 风格 | G27: 护甲SP | H27: 妨碍值EV | I27: 口袋容量 | J27: 描述 | K27: 特性
C28: 帽子
C29: 内搭
C30: 外套
C31: 下装
C32: 配饰

Sheet 背包卡
B2: 随身物品 | D2: 下方已有物品为示例，使用前请删除 | K2: 仓库 | M2: 下方已有物品为示例，使用前请删除
C4: 物品名称 | D4: 描述 | E4: 备注 | F4: 剩余数量 | G4: 所处位置 | L4: 物品名称 | M4: 描述 | N4: 备注 | O4: 剩余数量 | P4: 所处位置

Sheet 义体卡
C2: 义体统计 | E2: 下方已有义体为示例，使用前请删除 | N2: 精神状态 | P2: 仅供参考，不参与自动计算
I4: 总人性损失 | J4: 总人性上限损失 | N4: 当前人性 | O4: 人性上限 | P4: 共情 | Q4: 精神状态
I5: =SUM(I7:I55) -> 56 | J5: =SUM(J7:J55) -> 10 | N5: =人物卡!K32 -> 0 | O5: =人物卡!O32 -> 0 | P5: =人物卡!P22 -> 0 | Q5: =IF(P5<0,"严重赛博精神病",IF(P5=0,"赛博精神病",IF(P5=1,"分离性精神障碍",IF(P5=2,"边缘分离性精神障碍","健康")))) -> 赛博精神病
C6: 基础义体 | D6: 插槽 | E6: 插件 | F6: 安装设施 | G6: 描述和数据 | H6: 稀有度 | I6: 人性损失 | J6: 人性上限损失 | N6: 人性值变动记录
G7: 某赛博组件 | I7: 7 | J7: 2 | N7: 项目 | P7: 人性值变化 | Q7: 人性变化区分正负！
G8: 某赛博格组件 | I8: 14 | J8: 4
G9: 某生物改组件 | I9: 7 | J9: 0 | Q9: 人性损失不小于1的
G10: 某异人改造 | I10: 14 | J10: 0 | Q10: 义体减2人性上限
G11: 某全身赛博格改造 | I11: 17 | J11: 4 | Q11: 全身赛博格减4上限。
Q12: 义体安装并非直接
Q13: 等量损失人性上限
Q14: 常见易错点
N16: 临时消耗损失 | P16: =往来记录!Q61 -> 0
N19: 药物状态
N21: 是否成瘾 | O21: 药物名称 | P21: 备注
C38: 人性变动事件 | E38: 描述 | G38: 效果 | I38: 人性损失
C39: 低级享乐 | E39: 看了一晚上普通超梦 | G39: 恢复1d6人性 | I39: -3

Sheet 往来记录
C2: I.P.统计 | D2: 不参与自动计算，为记录用。 | K2: 往来记录 | M2: 不区分正负！ | Q2: 区分正负！
C4: I.P.点 | J4: 时间 | K4: 模组 | L4: 声望变更± | M4: 获得金钱+ | N4: 消耗金钱+ | O4: 获得物品 | P4: 失去物品 | Q4: 人性临时变更± | R4: I.P.变更± | S4: 影响来源 | T4: 任务备注 | U4: 重要的时刻
C5: 已获得 | D5: 职业消耗 | E5: 技能消耗 | F5: 剩余 | J5: 46203 | K5: 开卡
C6: =R61 -> 0 | D6: =SUM(F9:F18) -> 0 | E6: =SUM(F21:F60) -> 0 | F6: =C6-D6-E6 -> 0
C7: 职业成长表
C8: 职业名称 | D8: 初始等级 | E8: 成长等级 | F8: 消耗I.P.
C9: 摇滚小子
C10: 佣兵
C11: 网行者
C12: 技工
C13: 技医
C14: 媒体人
C15: 企业人
C16: 执法者
C17: 掮客
C18: 游民
C19: 技能成长表
C20: 技能名称 | D20: 原始技能 | E20: 成长技能 | F20: 消耗I.P.
C50: 属性 | D50: 初始等级 | E50: 成长等级 | F50: 锻炼结束时间
C51: 智力 | F51: 暂不开放
C52: 反应 | F52: 暂不开放
C53: 敏捷
C54: 技术 | F54: 暂不开放
C55: 酷 | F55: 暂不开放
C56: 意志 | F56: 暂不开放
C57: 运气 | F57: 暂不开放
C58: 移速
C59: 体格
C60: 共情 | F60: 暂不开放
C61: 注：锻炼消耗的金钱计入往来记录中 | K61: 合计 | L61: =SUM(L5:L60) -> 0 | M61: {=SUM(ABS(M5:M60))} -> 0 | N61: {=SUM(ABS(N5:N60))} -> 0 | Q61: =SUM(Q5:Q60) -> 0 | R61: =SUM(R5:R60) -> 0

Sheet 购物助手
B1: 购物清单生成器 | H1: 电子小票出口 | L1: 电子小票插入口 | P1: 购物清单解析器 | X1: =_xlfn.TEXTJOIN(":",TRUE,B2,C2,D2) -> 物品名（可备注稀有度等信息）:个数:单价 | Y1: =_xlfn.TEXTJOIN("|",TRUE,X3:X98)
B2: 物品名（可备注稀有度等信息） | C2: 个数 | D2: 单价 | E2: 单项总价 | F2: 合计 | H2: 打印小票 | L2: 读取小票 | P2: 物品名 | Q2: 个数 | R2: 单价 | S2: 单项总价 | T2: 合计
E3: =C3*D3 -> 0 | F3: =SUM(E$1:E$98) -> 0 | H3: =Y1 | P3: {=_xlfn.TEXTSPLIT(L3,":","|",FALSE(),,)} -> #VALUE! | S3: =Q3*R3 -> 0 | T3: =SUM(S$1:S$98) -> 0 | X3: =_xlfn.TEXTJOIN(":",TRUE,B3,C3,D3)
E4: =C4*D4 -> 0 | S4: =Q4*R4 -> 0 | X4: =_xlfn.TEXTJOIN(":",TRUE,B4,C4,D4)
E5: =C5*D5 -> 0 | S5: =Q5*R5 -> 0 | X5: =_xlfn.TEXTJOIN(":",TRUE,B5,C5,D5)
E6: =C6*D6 -> 0 | S6: =Q6*R6 -> 0 | X6: =_xlfn.TEXTJOIN(":",TRUE,B6,C6,D6)
E7: =C7*D7 -> 0 | S7: =Q7*R7 -> 0 | X7: =_xlfn.TEXTJOIN(":",TRUE,B7,C7,D7)
E8: =C8*D8 -> 0 | S8: =Q8*R8 -> 0 | X8: =_xlfn.TEXTJOIN(":",TRUE,B8,C8,D8)
E9: =C9*D9 -> 0 | S9: =Q9*R9 -> 0 | X9: =_xlfn.TEXTJOIN(":",TRUE,B9,C9,D9)
E10: =C10*D10 -> 0 | S10: =Q10*R10 -> 0 | X10: =_xlfn.TEXTJOIN(":",TRUE,B10,C10,D10)
E11: =C11*D11 -> 0 | S11: =Q11*R11 -> 0 | X11: =_xlfn.TEXTJOIN(":",TRUE,B11,C11,D11)
E12: =C12*D12 -> 0 | S12: =Q12*R12 -> 0 | X12: =_xlfn.TEXTJOIN(":",TRUE,B12,C12,D12)
E13: =C13*D13 -> 0 | S13: =Q13*R13 -> 0 | X13: =_xlfn.TEXTJOIN(":",TRUE,B13,C13,D13)
E14: =C14*D14 -> 0 | S14: =Q14*R14 -> 0 | X14: =_xlfn.TEXTJOIN(":",TRUE,B14,C14,D14)
E15: =C15*D15 -> 0 | S15: =Q15*R15 -> 0 | X15: =_xlfn.TEXTJOIN(":",TRUE,B15,C15,D15)
... E45: =C45*D45 -> 0 | S45: =Q45*R45 -> 0 | X45: =_xlfn.TEXTJOIN(":",TRUE,B45,C45,D45)
E46: =C46*D46 -> 0 | H46: 复制到右边的大框 | L46: 粘贴为纯文本 | S46: =Q46*R46 -> 0 | X46: =_xlfn.TEXTJOIN(":",TRUE,B46,C46,D46)
E47: =C47*D47 -> 0 | S47: =Q47*R47 -> 0 | X47: =_xlfn.TEXTJOIN(":",TRUE,B47,C47,D47)
E48: =C48*D48 -> 0 | S48: =Q48*R48 -> 0 | X48: =_xlfn.TEXTJOIN(":",TRUE,B48,C48,D48)
E49: =C49*D49 -> 0 | H49: 钱包 | L49: 衣食住行 | S49: =Q49*R49 -> 0 | X49: =_xlfn.TEXTJOIN(":",TRUE,B49,C49,D49)
E50: =C50*D50 -> 0 | I50: 专项预算不会自动计算 | S50: =Q50*R50 -> 0 | X50: =_xlfn.TEXTJOIN(":",TRUE,B50,C50,D50)
E51: =C51*D51 -> 0 | H51: 专项预算 | I51: 时尚预算 | L51: 食物 | N51: 花费 | S51: =Q51*R51 -> 0 | X51: =_xlfn.TEXTJOIN(":",TRUE,B51,C51,D51)
E52: =C52*D52 -> 0 | I52: 剩余 | S52: =Q52*R52 -> 0 | X52: =_xlfn.TEXTJOIN(":",TRUE,B52,C52,D52)
E53: =C53*D53 -> 0 | H53: 流动资金 | I53: 赞助 | L53: 住所 | N53: 花费 | S53: =Q53*R53 -> 0 | X53: =_xlfn.TEXTJOIN(":",TRUE,B53,C53,D53)
E54: =C54*D54 -> 0 | I54: 初始资金 | S54: =Q54*R54 -> 0 | X54: =_xlfn.TEXTJOIN(":",TRUE,B54,C54,D54)
E55: =C55*D55 -> 0 | I55: 往来收益 | J55: =往来记录!M61 -> 0 | L55: 水电 | N55: 花费 | S55: =Q55*R55 -> 0 | X55: =_xlfn.TEXTJOIN(":",TRUE,B55,C55,D55)
E56: =C56*D56 -> 0 | I56: 往来支出 | J56: =往来记录!N61 -> 0 | S56: =Q56*R56 -> 0 | X56: =_xlfn.TEXTJOIN(":",TRUE,B56,C56,D56)
E57: =C57*D57 -> 0 | I57: 特殊支出 | L57: 网络 | N57: 花费 | S57: =Q57*R57 -> 0 | X57: =_xlfn.TEXTJOIN(":",TRUE,B57,C57,D57)
E58: =C58*D58 -> 0 | I58: 总计 | J58: =J53+J54+J55-J56-J57 -> 0 | S58: =Q58*R58 -> 0 | X58: =_xlfn.TEXTJOIN(":",TRUE,B58,C58,D58)
E59: =C59*D59 -> 0 | L59: 本月已支付 | N59: 月开销 | S59: =Q59*R59 -> 0 | X59: =_xlfn.TEXTJOIN(":",TRUE,B59,C59,D59)
E60: =C60*D60 -> 0 | L60: 已录入记录 | N60: =SUM(N52+N54+N56+N58) -> 0 | S60: =Q60*R60 -> 0 | X60: =_xlfn.TEXTJOIN(":",TRUE,B60,C60,D60)
E61: =C61*D61 -> 0 | S61: =Q61*R61 -> 0 | X61: =_xlfn.TEXTJOIN(":",TRUE,B61,C61,D61)
E62: =C62*D62 -> 0 | S62: =Q62*R62 -> 0 | X62: =_xlfn.TEXTJOIN(":",TRUE,B62,C62,D62)
E63: =C63*D63 -> 0 | S63: =Q63*R63 -> 0 | X63: =_xlfn.TEXTJOIN(":",TRUE,B63,C63,D63)
E64: =C64*D64 -> 0 | S64: =Q64*R64 -> 0 | X64: =_xlfn.TEXTJOIN(":",TRUE,B64,C64,D64)
E65: =C65*D65 -> 0 | S65: =Q65*R65 -> 0 | X65: =_xlfn.TEXTJOIN(":",TRUE,B65,C65,D65)
E66: =C66*D66 -> 0 | S66: =Q66*R66 -> 0 | X66: =_xlfn.TEXTJOIN(":",TRUE,B66,C66,D66)
E67: =C67*D67 -> 0 | S67: =Q67*R67 -> 0 | X67: =_xlfn.TEXTJOIN(":",TRUE,B67,C67,D67)
E68: =C68*D68 -> 0 | S68: =Q68*R68 -> 0 | X68: =_xlfn.TEXTJOIN(":",TRUE,B68,C68,D68)
E69: =C69*D69 -> 0 | S69: =Q69*R69 -> 0 | X69: =_xlfn.TEXTJOIN(":",TRUE,B69,C69,D69)
E70: =C70*D70 -> 0 | S70: =Q70*R70 -> 0 | X70: =_xlfn.TEXTJOIN(":",TRUE,B70,C70,D70)
E71: =C71*D71 -> 0 | S71: =Q71*R71 -> 0 | X71: =_xlfn.TEXTJOIN(":",TRUE,B71,C71,D71)
E72: =C72*D72 -> 0 | S72: =Q72*R72 -> 0 | X72: =_xlfn.TEXTJOIN(":",TRUE,B72,C72,D72)
... E98: =C98*D98 -> 0 | S98: =Q98*R98 -> 0 | X98: =_xlfn.TEXTJOIN(":",TRUE,B98,C98,D98)

Sheet RP卡
C2: 生命路径 | H2: 亲朋好友 | T2: 精神病症状
C4: 风格 | H4: 名字 | I4: 你们的关系 | L4: 详细描述
C5: 文化区域
C6: 母语
C7: 性格
C8: 发型
C9: 衣着风格
C10: 动机
C11: 落草的缘由
C12: 最看重什么
C13: 最在乎的人
C14: 对人类观点
C15: 宝物 | H15: 爱情
C16: 目标
C17: 家庭背景及其他 | H17: 名字 | I17: 发生了什么 | L17: 详细描述
C18: 原生家庭
C19: 童年环境
C20: 家庭危机
C26: 基于职业的生命路径
H28: 人物背景故事
C40: 敌人
C42: 名字 | D42: 关系如何 | E42: 什么导致的 | J42: 他会怎么样来找你 | M42: 你打算怎么做 | P42: 详细描述

Sheet 网行卡
A1: 赛博碟版/网行椅
A2: 设备型号 | B2: 设备改造 | C2: 最大算力 | D2: 剩余算力 | E2: 描述 | F2: 稀有度 | G2: 价格
A3: 高手玩家电竞超梦椅 | E3: 那些乳臭未干的小屁孩们要么坐在上面打游戏，要么坐在上面打飞机。但也有些特别的聪明小孩会用那额外的处理芯片来潜入暗网。算力+2，潜入暗网的交互界面检定+1 | F3: R | G3: 400 | H3: 示例，记得删除
A6: 掌上代理软件 | E6: 掌上助理的软件，部分也有网页端。可以随时使用
A7: 软件名称 | B7: 会员制 | C7: 网页端 | D7: 所属公司 | E7: 描述 | F7: 订阅费 | G7: 安全性
B8: 次/月/年买断 | C8: 是/否
A9: 精灵战线 Online | B9: 月 | C9: 否 | D9: 世嘉达利 | E9: 时下最流行的MMORPG，在全球拥有千万规模的用户账号，日活量高达八十七万。它是一个关于剑与魔法的奇幻世界，有奇幻题材常见的精灵、矮人、龙……它有多个平台的版本可以使用，无论是普通的掌上代理还是尖端的黑客椅，乃至最先进的超梦体验仪，都可以进入游玩。但不同设备的玩家之间性能亦有差异，官方比较推荐使用超梦设备进行游玩。 | F9: 7 | G9: 高 | H9: 示例，记得删除
A11: 网行魔偶 | E11: 必须要搭配电子战平台或者义体才能使用，对目标单位方向释放的高频电波
A12: 软件名称 | B12: 稀有度 | C12: 算力占用 | D12: 消耗行动 | E12: 描述 | F12: 价格
A13: 终端定位 | B13: N | C13: 1 | D13: 1 | E13: 锁定目标终端、服务器或者黑客所在的位置，对于可移动的目标，只会显示其当前位置。通常为维修工使用。 | F13: 免费 | H13: 示例，记得删除
A16: 网络攻防程序 | E16: 入侵网络建筑时，双方所使用的常见程序。
A17: 程序名称 | B17: ATK/DEF | C17: 算力占用 | D17: 消耗行动 | E17: 效果 | F17: 价格 | G17: 稀有度
A18: 利刃 | B18: 1/0 | C18: 1 | D18: 0 | E18: 击穿一个敌方的防御型程序后，ATK+1。 | F18: 免费 | G18: N | H18: 示例，记得删除

Sheet 载具卡
C1: 载具表 | D1: 以下为示例，使用前请删除
C3: 名称 | D3: 种类 | E3: 稀有度 | F3: 座位 | G3: SDP/SP | H3: 飞/陆 | I3: 战斗速度 | J3: 最高时速 | K3: 续航 | L3: 配件槽 | M3: 油耗 | N3: 价格 | P3: 名称 | Q3: 类型 | R3: 单发射速 | S3: 全自动弹幕 | T3: 精度 | U3: 伤害 | V3: 穿甲等级 | W3: 描述 | X3: 价格 | Y3: 稀有度 | Z3: 射程
C4: 特拉克斯 388 杰斐逊 | D4: 轿车 | E4: SR | F4: 2 | G4: 100/16 | H4: 陆 | I4: 10/15/20/26 | J4: 180km/h | K4: 700km | L4: 3（M） | M4: 中 | N4: 55000 | P4: 120mm滑膛炮 | Q4: 加农炮（重） | R4: 1 | S4: / | T4: 0 | U4: 10D12+50 | V4: 反坦克 | W4: 常见的120mm重型滑膛炮，被普遍安装在现代主战坦克和重型步行机上，是当今最常见的前线反装甲火力配置。也能发射高爆弹药用以反人员和工事。 | X4: 120000 | Y4: SSR
C5: 描述 | P5: 等待正式版
C6: 特拉克斯系列一直是企业中层商务人士的首选汽车，它优雅、令人尊敬，最重要的是——它很安全。它从上到下覆盖着装甲，可以穿越地雷爆炸，而它的防弹窗户可以挡住大口径子弹。缺点是什么？尽管其拥有强大的引擎，能够达到令人眼花缭乱的速度，但由于重量惊人，它加速缓慢。但迟到总比不到好。更不用说完好无损了。它的车门和车身自带防弹改装，其玻璃也可以当作掩体，具有11sp和10hp。
C7: 底盘改造 | D7: 描述 | N7: 价格
C8: 悬浮底板 | D8: 将底盘改造为浮空车底盘，续航里程减半，但你可以飞行至最高离地二十米的高度，你驾驶该载具使用的技能从地面载具驾驶更改为飞行载具驾驶。其改造价格是车辆的四分之一 | N8: 13750
C9: 引擎改造 | D9: 描述 | N9: 价格
C10: 醇二引擎 | D10: 将引擎改成醇二引擎，增设油箱的弱点（-8，瞄准时造成2倍伤害），但是车体正面的引擎护甲等级上升一级。其油耗随其类型改变（摩托车低、）其改造价格是车辆的八分之一 | N10: 6875
C11: 观瞄改造 | D11: 描述 | N11: 价格
C12: C-9981车用环绕监控 | D12: 投影窗 将车窗改造为7sp 5sdp的掩体 常见的民用车辆周身投影监控装置，具备基础的图像识别功能，通常是为了辅助康陶的浮空车AI进行自动驾驶使用。 | N12: 800
C13: 驾驶舱改造 | D13: 描述 | N13: 价格
C14: 人体工程学式飞控操作台 | D14: 需要投影窗 类似浮空车和飞机的智能操作系统，可以让驾驶者舒服地躺在座椅上，用车体的监视系统或是无人机来观察周围的情况，并使用类似游戏手柄的操作杆来进行驾驶。极大地缓解了公路驾驶的疲劳。驾驶技能+2，但一旦车窗报废，或是无人机被摧毁，驾驶员在当回合不能进行任何操作，需要过一个DV15的专注检定才能保证车辆不失控。 | N14: 1000
C15: 车舱改造 | D15: 描述 | N15: 价格
C16: 防弹车窗 | D16: 使用加厚的钢化防弹玻璃使车窗变成一面提供了4减伤（不可减免全威力及以上等级火力）的掩体，在面对更高等级穿甲时无效。在被击穿三次后报废。不与棺式驾驶舱兼容 | N16: 800
C17: 尾舱改造 | D17: 描述 | N17: 价格
C18: 额外座椅 | D18: 为车辆额外添加2/4个座椅，但牺牲了后舱的空间，无法将后舱改造为其他形态。 | N18: 300
C19: 车头改造 | D19: 描述 | N19: 价格
C20: 撞角 | D20: 为车头添加一个冲撞用的铲斗，当以撞击的方式伤害他人或载具时，你造成伤害的乘数+1 | N20: 200
C21: 车顶改造 | D21: 描述 | N21: 价格
C22: 探照灯 | D22: 安装一个可以自由操作的大功率探照灯，指向50m以内的目标时，目标需要过一个DV14的反应检定，失败则受到眼睛受损的严重伤势三回合。以此方式造成的严重伤势不会造成额外伤害。 | N22: 100
C23: 装甲改造 | D23: 描述 | N23: 价格
C24: 中型载具装甲 | D24: 使载具+4sp，最高24。若原本sp小于18，则提升至18sp.获得【分布填充2】特性以及4点减伤。但需要减少十分之一的最高时速，并-1战斗速度。只能安装一种装甲改造。 用轻型装甲钢包裹全车，使其可以抵挡步兵火力。改造价格为原载具的八分之一。 | N24: 6875
C25: 特殊改造 | D25: 描述 | N25: 价格
C26: 自律化炮塔 | D26: 需要投影窗/HUD 让你的炮塔更加智能化，乘员只需要在HUD上标记敌方单位，炮塔就能自动对该单位开火，只能安装在低级炮塔上。炮塔的战斗技能为14，加价2000可以购买高级战斗芯片，升级到16。加价5000升级至20 | N26: 5000
C27: 配件改造 | D27: 类型 | E27: 描述 | N27: 价格
C28: 重型轮胎 | D28: M | E28: 轮胎的摧毁阈值+20，且将护甲等级提升至超重甲。只能安装在使用轮胎的陆行载具上。 | N28: 1000
C29: 野战雷达 | D29: 2M | E29: 占据两个观瞄配件槽 军用载具的野战雷达，用以侦测5km内无遮挡的载具、人性轮廓和建筑物。若在空中50m以上高度使用，则侦测距离翻倍。 | N29: 10000
M33: 合计费用： | N33: =SUM(N3:N32) -> 101700

Sheet ACPA卡
B2: ACPA表 | H2: 以下为示例，使用前请删除，注！示例价格不等于实际价格，请以最新版本新黑市为准
C4: 名称 | D4: 类型 | E4: 装甲 | F4: 耐久 | G4: 槽位 | J4: 成本 | W4: 成本
C5: 服部 | D5: 轻 | E5: =SUM(E7:E74) -> 96 | F5: =SUM(F7:F74) -> 172 | G5: =SUM(G7:G74) -> 13 | J5: =SUM(J7:J74) -> 176200 | W5: =SUM(W7:W70) -> 11900
C6: 组件名 | D6: 类型 | E6: 装甲 | F6: 耐久 | G6: 槽位 | I6: 稀有度 | J6: 成本 | L6: 武器 | M6: 射速 | N6: 类型 | O6: 弹容（弹药） | P6: 精准 | Q6: 伤害 | R6: 穿甲等级 | S6: 改件槽 | T6: 全自动公式 | U6: 射程 | V6: 稀有度 | W6: 价格
C7: 头部组件 | L7: 宪法军工 .50重机枪 | M7: 仅全自动 | N7: 机枪（轻） | O7: 100（.50BMG） | P7: 0 | Q7: / | R7: 轻反器材 | S7: 2 | T7: 2x2 / 3x8 | U7: 600m | V7: R | W7: 3000
C8: 服部原装高功能潜入系统 | D8: 轻 | E8: 15 | F8: 20 | G8: 7 | H8: 反应+1，虚拟实景交互界面 | I8: SSR | J8: 20500 | L8: 描述
C9: 头部系统改造 | D9: 加成 | G9: 槽位 | H9: 描述 | I9: 稀有度 | J9: 成本 | L9: 重机枪 最常见的ACPA武装之一，有大量的遗留库存，因此价格十分实惠。通常是固定在吉普车上的自卫武器。可以被轻型ACPA双手持握，也可以安装在重型ACPA的手臂上。
C10: 虚拟实景交互界面 | D10: 先攻+2，反应+2 | G10: 0 | H10: 爽飙装甲的唯一方式，虚拟实境界面为装甲骑兵解析他所处的环境，并以复杂的图形和有限的听觉警告向他展示信息。 在这一级的系统上，驾驶动力装甲与进行网跑已没有什么区别。熟练的装甲骑兵在装备此系统后将变得极为致命。整合了防护眩光、激光夜视仪、远程瞄准、热成像、图像增强、卫星上行链路、多目标瞄准系统和拾音降噪侦测系统 | I10: SSR | J10: 0
C11: 防护炫光 | D11: / | G11: 0 | H11: 免疫闪光弹和高功率手电筒的影响。 | I11: N | J11: 0
C12: 激光夜视仪 | D12: / | G12: 0 | H12: 提供夜视功能，在微光和无光环境下可视距离3km，并可以看见红外信号。 | I12: SR | J12: 0
C13: 远程瞄准 | D13: / | G13: 0 | H13: 提供最远5km的望远功能，并可以通过智能武器上传链路提供弹道瞄准。 | I13: SR | J13: 0 | L13: 配件 | M13: 描述 | V13: 占用位置 | W13: 占用槽数
C14: 热成像 | D14: / | G14: 0 | H14: 提供热成像视觉功能，可以探测2km内的热能信号，并反馈在视觉上。可以穿透常规烟雾，不能穿透硬物。 | I14: SR | J14: 0
C15: 图像增强 | D15: 先攻+1 | G15: 0 | H15: 配有更宽的观察区域和 "快速变焦"，觉察系技能出1可重骰一次。 | I15: SR | J15: 0
C16: 卫星上行链路 | D16: / | G16: 0 | H16: 允许动力装甲直接与轨道上的通信或侦察卫星连接，并在露天野外区域保持通讯信号良好。 | I16: R | J16: 0
C17: 多目标瞄准系统 | D17: / | G17: 0 | H17: 可以将多件已链接的进攻系统/手持武器整合进自己战斗动作的一部分。但本回合每多用一件武器，命中就额外-2。 | I17: SR | J17: 0
C18: 拾音降噪侦测系统 | D18: 察觉（听）+2 | G18: 0 | H18: 能精确识别并过滤战场上的噪音，从中分拣出有用的信息。可以听见最远70米外的细微动静。 | I18: SR | J18: 0
C19: 整合型战场火控装置 | D19: 精准度+1 | G19: -1 | H19: 具备多目标瞄准系统功能，和智能索敌锁定系统冲突。你可以随意【锁定】任何目标，但一回合最多一个。若整合的武器系统中带有需要锁定的武器，则免去锁定需要的动作。 | I19: SSR | J19: 5000 | L19: 武器 | M19: 射速 | N19: 类型 | O19: 弹容（弹药） | P19: 精准 | Q19: 伤害 | R19: 穿甲等级 | S19: 改件槽 | T19: 全自动公式 | U19: 射程 | V19: 稀有度 | W19: 价格
C20: 身体组件 | L20: IFAR-8 火箭突击炮 | M20: 1 | N20: 重武（重） | O20: 4（火箭弹） | P20: 1 | Q20: 6D12 | R20: 重反器材 | S20: 2 | T20: / | U20: 1.7km | V20: R | W20: 8900
C21: 服部原装线性框架 | D21: 轻 | E21: 18 | F21: 45 | G21: 6 | H21: 反应+1，敏捷+1 体格14，可以闪避子弹 | I21: SR | J21: 35000 | L21: 描述
C22: 身体系统改造 | D22: 加成 | G22: 槽位 | H22: 描述 | I22: 稀有度 | J22: 成本 | L22: 无后座炮 发射火箭弹药和导弹的大口径无后座炮，战场上的装甲克星。通常会被安装在肩膀的武器系统上，少数时候由轻型ACPA携带，如同步兵一样肩扛发射。弹药类型和效果同单兵火箭弹。只能安装智能链接
C23: “武士道”兴奋剂注射器 | D23: / | G23: -1 | H23: 这套简陋的系统实际上并不能让驾驶员活下来，只是能让他活着。它里面配备了两种特制的兴奋剂，一种在战斗中注射，另一种在驾驶员遭到重创时注射。前者是臭名昭著的黑蕾丝，而后者则是令人恐惧的“飙血者”。它可以让驾驶员保持极度兴奋状态，无视身上的伤口和疼痛，继续驾驶直到失血过多而死。而它也会如其名字一样加速驾驶员的流血速度。许多报告显示重创的荒坂装甲骑兵会在临死前爆发出惊人的战斗力，是无数军科士兵的噩梦。 | I23: N | J23: 600
C24: 纳米自修复系统 | D24: / | G24: -1 | H24: 一套由编程式纳米蜂群和液态金属原料组成的系统，可以在战场上及时对受损部位进行修补。每回合能恢复部位2点SDP，全身最多恢复20点。 | I24: SSR | J24: 10000
L26: 配件 | M26: 描述 | V26: 占用位置 | W26: 占用槽数
C31: 右手部组件
C32: 服部原装仿生肌肉束 | D32: 轻 | E32: 15 | F32: 27 | G32: 2 | H32: 高增强，武术+2 | I32: SR | J32: 21000 | L32: 武器 | M32: 射速 | N32: 类型 | O32: 弹容（弹药） | P32: 精准 | Q32: 伤害 | R32: 穿甲等级 | S32: 改件槽 | T32: 全自动公式 | U32: 射程 | V32: 稀有度 | W32: 价格
C33: 右手部系统改造 | D33: 加成 | G33: 槽位 | H33: 描述 | I33: 稀有度 | J33: 成本
C34: 热能武士刀 | D34: / | G34: -1 | H34: 数据同热能武士刀，但伤害额外加2粒骰子，且拥有重反器材级别的穿甲能力 | I34: SR | J34: 2300 | L34: 描述
C35: 液压重拳 | D35: / | G35: -1 | H35: 拳击力度增加1D6，不能和武器挂架共存。可以和高级武器挂架共存。 | I35: SR | J35: 1800
H36: 注：因左右手相同不叠加加成，故以不同部件示范
L39: 配件 | M39: 描述 | V39: 占用位置 | W39: 占用槽数
C42: 左手部组件
C43: “蜘蛛骨”强攻手甲 | D43: 中 | E43: 18 | F43: 40 | G43: 4 | H43: 超控增强，额外附带一只同样灵敏的机械手臂，损失20hp后，额外的机械臂损坏 | I43: SSR | J43: 44000
C44: 左手部系统改造 | D44: 加成 | G44: 槽位 | H44: 描述 | I44: 稀有度 | J44: 成本
C45: 电子干扰指向性天线 | D45: / | G45: -1 | H45: 每回合一次，干扰一发锁定你的导弹，使其脱离锁定并偏离。无法干扰无制导火箭弹，只能安装一次。 | I45: SR | J45: 2000 | L45: 武器 | M45: 射速 | N45: 类型 | O45: 弹容（弹药） | P45: 精准 | Q45: 伤害 | R45: 穿甲等级 | S45: 改件槽 | T45: 全自动公式 | U45: 射程 | V45: 稀有度 | W45: 价格
H46: 注：因左右手相同不叠加加成，故以不同部件示范
L47: 描述
L52: 配件 | M52: 描述 | V52: 占用位置 | W52: 占用槽数
C53: 右腿部组件
C54: “猫足”无声靴 | D54: 轻 | E54: 15 | F54: 20 | G54: 2 | H54: 无声移动，敏捷+1 | I54: SR | J54: 14000
C55: 右腿部系统改造 | D55: 加成 | G55: 槽位 | H55: 描述 | I55: 稀有度 | J55: 成本
C56: 全向动力轮 | D56: 移动+1 | G56: -2 | H56: 移动+2，只能安装在轻型ACPA身上，这种极其灵敏的全向轮可以在熟练的装甲骑兵手上达到极其夸张的机动性。使ACPA可以闪避200m外朝其射击的火力。 | I56: SSR | J56: 3000
L58: 武器 | M58: 射速 | N58: 类型 | O58: 弹容（弹药） | P58: 精准 | Q58: 伤害 | R58: 穿甲等级 | S58: 改件槽 | T58: 全自动公式 | U58: 射程 | V58: 稀有度 | W58: 价格
L60: 描述
C64: 左腿部组件
C65: “猫足”无声靴 | D65: 轻 | E65: 15 | F65: 20 | G65: 2 | H65: 无声移动，敏捷+1 | I65: SR | J65: 14000 | L65: 配件 | M65: 描述 | V65: 占用位置 | W65: 占用槽数
C66: 左腿部系统改造 | D66: 加成 | G66: 槽位 | H66: 描述 | I66: 稀有度 | J66: 成本
C67: 全向动力轮 | D67: 移动+1 | G67: -2 | H67: 移动+2，只能安装在轻型ACPA身上，这种极其灵敏的全向轮可以在熟练的装甲骑兵手上达到极其夸张的机动性。使ACPA可以闪避200m外朝其射击的火力。 | I67: SSR | J67: 3000

Sheet 鲨包速查V1.91
A1: 新射表： | J1: 躯干严重伤势表 | P1: 暴击表
A2: 射表 | B2: 0~12m | C2: 13~25m | D2: 26~50m | E2: 51~100m | F2: 101~250 | G2: 251~500 | H2: 501~1km | J2: 出目 | K2: 伤势 | L2: 伤势效果 | M2: 紧急处理 | N2: 医治 | P2: D4=出目4个4
A3: 手枪 | B3: 8 | C3: 14 | D3: 20 | E3: 26 | F3: 30 | G3: / | H3: / | J3: 2 | K3: 断臂 | L3: 失去断掉的那只手臂.那只手里拿着的任何东西立刻掉落. 基础死亡豁免惩罚+1 | M3: / | N3: 需肢体移植 | P3: D6=出目双6
A4: 冲锋枪 | B4: 10 | C4: 12 | D4: 16 | E4: 20 | F4: 25 | G4: 30 | H4: / | J4: 3 | K4: 肠胃撕裂 | L4: 每回合损失1体格，影响生命上限和相关豁免，下限为2。基础死亡豁免惩罚+1。30分钟后未得到有效处理即死亡。 | M4: 强化17 | N4: 需器官移植 | P4: D8=出目双7+
A5: 霰弹（独） | B5: 11 | C5: 13 | D5: 16 | E5: 18 | F5: 23 | G5: / | H5: / | J5: 4 | K5: 气胸 | L5: 每回合损失1敏捷，下限为2。基础死亡豁免惩罚+1。30分钟后未得到有效处理即死亡。 | M5: 强化15 | N5: 需器官移植 | P5: D10=出目双9+/单10
A6: 突击步枪 | B6: 12 | C6: 13 | D6: 14 | E6: 16 | F6: 20 | G6: 24 | H6: 28 | J6: 5 | K6: 断手 | L6: 失去断掉的那只手.那只手里拿着的任何东西立刻掉落. 基础死亡豁免惩罚+1. | M6: / | N6: 需肢体移植 | P6: D12=出目单11/单12
A7: 弓弩 | B7: 14 | C7: 10 | D7: 13 | E7: 17 | F7: 21 | G7: / | H7: / | P7: D20=出目单16~20
A8: 狙击步枪 | B8: 16 | C8: 14 | D8: 12 | E8: 14 | F8: 16 | G8: 18 | H8: 22 | J8: 6 | K8: 手臂骨折 | L8: 骨折的手臂无法再用来干别的事了. 那只手里拿着的任何东西立刻掉落. | M8: 急救13 | N8: 强化12/手术8
A9: 榴弹 | B9: 14 | C9: 15 | D9: 17 | E9: 19 | F9: 21 | G9: 25 | H9: 28 | J9: 7 | K9: 体内异物 | L9: 在每个你徒步行进了超过 4m/yds 的回合, 你都要重新受到这个严重伤势的额外伤害,直接从生命值里扣除. | M9: 强化13 | N9: 紧急处理即可永久移除
A10: 火箭 | B10: / | C10: 14 | D10: 16 | E10: 18 | F10: 18 | G10: 24 | H10: 30
J11: 8 | K11: 腿骨折 | L11: -4移动和闪避（最小为1） | M11: 急救10 | N11: 强化12/手术8
A12: 射表 | B12: 0~6m | C12: 7~12m | D12: 13~25m | E12: 26~50m | F12: 50~100m | J12: 9 | K12: 动脉破损 | L12: 每回合损失相当于体格的生命值。 | M12: 急救10 | N12: 紧急处理即可永久移除
A13: 火焰喷射器 | B13: 14 | C13: 10 | D13: 17 | E13: 20 | F13: 28
A14: 全自动： | J14: 10 | K14: 脊柱受伤 | L14: 跌倒在地，在之后的两回合内被迫进入趴下状态无法起身，且一切动作-2。基础死亡豁免惩罚 +1. | M14: 强化15 | N14: 手术15
A15: 射表 | B15: 0~12m | C15: 13~25m | D15: 26~50m | E15: 51~100m | F15: 101~250 | G15: 251~500 | H15: 501~1km | J15: 11 | K15: 肾/肝爆碎 | L15: 因为剧痛而跳过一回合，下一回合开始你的所有动作-2，直到被移除。30分钟后未得到有效处理即死亡。 | M15: 强化17 | N15: 需器官移植
A16: 冲锋枪 | B16: 12 | C16: 15 | D16: 20 | E16: 25 | F16: 30 | G16: / | H16: / | J16: 12 | K16: 断腿 | L16: 失去断掉的那条腿. -6 移动 (最小为1) 你无法闪避攻击.基础死亡豁免惩罚+1 | M16: / | N16: 需肢体移植
A17: 突击步枪 | B17: 14 | C17: 16 | D17: 18 | E17: 20 | F17: 24 | G17: 28 | H17: 32
J18: 头部严重伤势表
A19: 甲弹对抗 | B19: 4-9 | C19: 10-14 | D19: 15-19 | E19: 20-25 | F19: 26-32 | G19: 33-40 | H19: 41+ | J19: 2 | K19: 目盲 | L19: 双眼暂时失明，-10战斗技能、闪避和所有需要视觉的感知鉴定. | M19: / | N19: 手术17
A20: 名称 | B20: 轻甲 | C20: 中甲 | D20: 重甲 | E20: 超重甲 | F20: 战车甲 | G20: 坦克 | H20: 工事 | J20: 3 | K20: 脑损伤 | L20: -2 所有行动. 基础死亡豁免惩罚+1. | M20: 强化15 | N20: 手术17
A21: 手枪 | B21: 半穿 | C21: 微穿 | D21: 不可 | E21: 不可 | F21: 不可 | G21: 不可 | H21: 不可 | J21: 4 | K21: 脑震荡 | L21: 跳过一回合，下次大失败时会重复触发。 | M21: / | N21: 手术13
A22: 重手枪 | B22: 全穿 | C22: 半穿 | D22: 微穿 | E22: 不可 | F22: 不可 | G22: 不可 | H22: 不可 | J22: 5 | K22: 下颌粉碎 | L22: 因剧痛导致专注和闪避减半，无法说话，COOL-4。 | M22: / | N22: 手术17
A23: 中威力 | B23: 全穿 | C23: 全穿 | D23: 半穿 | E23: 微穿 | F23: 不可 | G23: 不可 | H23: 不可
A24: 全威力 | B24: 全穿 | C24: 全穿 | D24: 全穿 | E24: 半穿 | F24: 微穿 | G24: 不可 | H24: 不可 | J24: 6 | K24: 额叶损伤 | L24: 在被移除之前，获得一个赛博精神病的“应激症状”，每次大失败就会触发。 | M24: 强化15 | N24: 强化/手术13
A25: 轻反器 | B25: 全穿 | C25: 全穿 | D25: 全穿 | E25: 全穿 | F25: 半穿 | G25: 微穿 | H25: 不可 | J25: 7 | K25: 头部异物 | L25: 在每个你徒步行进了超过 4m/yds 的回合, 你都要重新受到这个严重伤势的额外伤害,直接从生命值里扣除. | M25: 急救/ | N25: 紧急处理即可永久移除
A26: 重反器 | B26: 全穿 | C26: 全穿 | D26: 全穿 | E26: 全穿 | F26: 全穿 | G26: 半穿 | H26: 微穿 | M26: 强化13
A27: 反坦克 | B27: 全穿 | C27: 全穿 | D27: 全穿 | E27: 全穿 | F27: 全穿 | G27: 全穿 | H27: 半穿 | J27: 8 | K27: 失去眼睛 | L27: 失去一只眼睛，-4 攻击、闪避和所有需要视觉的感知鉴定. | M27: / | N27: 需器官移植
A28: 全穿：穿透护甲后造成的伤害全部正常结算 | J28: 9 | K28: 颅骨骨裂 | L28: 瞄准你头部的精确射击造成的伤害在减去护甲之后倍数变为3. 基础死亡豁免惩罚 +1. | M28: 强化15 | N28: 紧急处理即可永久移除
A30: 半穿：穿透护甲后造成的伤害折半计算（向下取舍） | J30: 10 | K30: 耳聋 | L30: 所有需要听力的感知鉴定和闪避-4，每次承受超过5的伤害就会跌倒在地。基础死亡豁免惩罚 +1. | M30: / | N30: 手术13
A31: 微穿：穿透护甲后造成的伤害只取1（例如5d6，即便穿甲部分有10，最终也只造成1伤害，部分特殊tag可能有额外伤害） | J31: 11 | K31: 动脉破损 | L31: 每回合损失相当于自身体格的生命值。 | M31: 急救10 | N31: 紧急处理即可永久移除
J32: 12 | K32: 开放性脑损伤 | L32: 在被移除之前，获得一个赛博精神病的“长期症状”，智力和意志-2（最低1）。30分钟之内得不到有效处理即死亡。 | M32: 强化17 | N32: 手术17
A33: 不可：无论最终伤害是否高于护甲，该类型伤害都无法造成实际损害
A34: 霰弹通常算作重手枪级别的穿甲能力，而独头弹则是中间威力级。火焰和榴弹有单独的穿甲能力说明。近战武器如果没有特别标注，则都是全威力的穿甲等级。 当护甲数值因为各种原因下降时，其所属等级也会下降。且只有全穿或半穿时才能正常造成严重伤势。但是，即便武器或者弹药有“先降低护甲再结算”的描述，也不会改变对方护甲的防护等级。武器以全自动命中着甲目标时且成功穿透造伤时，护甲下降相当于本次全自动命中数的数值，无论什么情况下，“不可”都无法造成任何护甲损伤和生命损伤。 | J34: 部位 | K34: 瞄准减值 | L34: 效果
J35: 头部 | K35: -8 | L35: 穿透目标头部护甲后的最终伤害翻倍。若最终伤害大于目标的一半HP，则直接杀死目标。（对玩家或者部分boss可不应用后一段效果）
J36: 手臂 | K36: -6 | L36: 若穿甲后的伤害大于5，立刻造成手臂骨折的严重伤势效果。若伤害骰出了严重伤势，则更改为断臂。
J37: 腿部 | K37: -4 | L37: 若穿甲后的伤害大于5，立刻造成腿部骨折的严重伤势效果，若伤害骰出了严重伤势，则更改为断腿
J38: 裆部 | K38: -10 | L38: 若穿甲后的伤害大于5，角色立刻因为剧痛倒地，丧失行动能力1d4轮，视为特殊的严重伤势。若对方是赛博格或者拥有无视严重伤势的义体，则同样无视此效果。该部位受到腿部护甲保护。
A40: ACPA射表 | K40: 属性关联表
A41: 射表 | B41: 0~12m | C41: 13~25m | D41: 26~100m | E41: 101~500m | F41: 501~1km | G41: 1km~2km | H41: 2km~4km | K41: 体格 | L41: 效果
A42: 重机枪 | B42: 16 | C42: 14 | D42: 12 | E42: 16 | F42: 20 | G42: 25 | H42: / | K42: 0~3 | L42: 徒手、投掷和近战武器伤害骰-1（最低1）
A43: 机炮 | B43: 18 | C43: 16 | D43: 12 | E43: 14 | F43: 18 | G43: 22 | H43: / | K43: 4~7 | L43: 无
A44: 速射炮 | B44: 20 | C44: 18 | D44: 14 | E44: 12 | F44: 13 | G44: 16 | H44: 20 | K44: 8~11 | L44: 徒手、近战武器伤害骰+1,投掷伤害值+2
A45: 加农炮 | B45: / | C45: 22 | D45: 18 | E45: 13 | F45: 12 | G45: 14 | H45: 18 | K45: 12~15 | L45: 徒手、近战武器伤害骰+2,投掷伤害值+4
A46: 无后座 | B46: 28 | C46: 18 | D46: 12 | E46: 14 | F46: 18 | G46: 22 | H46: 25 | K46: 16~19 | L46: 徒手、近战武器伤害骰+3,投掷伤害值+6
A47: 火箭 | B47: / | C47: 22 | D47: 18 | E47: 14 | F47: 18 | G47: 24 | H47: 30 | K47: 20+ | L47: 徒手、近战武器伤害骰+4,投掷伤害值+8
K48: 敏捷 | L48: 效果
A49: 射表 | B49: 0~100m | C49: 101~300m | D49: 301~500m | E49: 501~1km | F49: 1km~2km | G49: 2km~5km | H49: 5km~10km | K49: 0~6 | L49: 无
A50: 迫击 | B50: / | C50: 20 | D50: 18 | E50: 15 | F50: 13 | G50: 18 | H50: 24 | K50: 7~11 | L50: 徒手、投掷、弓箭和近战武器的ROF额外+1
K51: 12~15 | L51: 徒手、投掷、弓箭和近战武器的ROF额外+2
A52: 全自动 | B52: 0~12m | C52: 13~25m | D52: 26~100m | E52: 101~500m | F52: 501~1km | G52: 1km~2km | H52: 2km~4km | K52: 16~20 | L52: 徒手、投掷、弓箭和近战武器的ROF额外+3
A53: 重机枪 | B53: 18 | C53: 14 | D53: 16 | E53: 18 | F53: 22 | G53: 30 | H53: / | K53: 20+ | L53: 徒手、投掷、弓箭和近战武器的ROF额外+4
A54: 机炮 | B54: 24 | C54: 18 | D54: 15 | E54: 16 | F54: 20 | G54: 28 | H54: /
A55: 速射炮 | B55: 30 | C55: 23 | D55: 18 | E55: 15 | F55: 19 | G55: 26 | H55: 30 | J55: ACPA损坏表
J56: 1~11：躯干 | L56: 躯干损坏：ACPA报废，除非花费三个动作将其脱下，否则该装甲具有8的EV。
J58: 12~13：左手 | L58: 手臂损坏：-2敏捷，-2体格，-1反应，重武器需要部署，安置于手上的系统失效。
J59: 14~15：右手
J60: 16~17：左腿 | L60: 腿部损坏：-2速度，-2体格，不能进行闪避动作。安装在腿部的系统失效。
J61: 18~19：右腿
J62: 20：头部 | L62: 头部损坏：无反应加成，现实交互界面系统失效，任何安装在头部的系统也失效。
